structuredsnip/__init__.py
structuredsnip/main.py
structuredsnip/prompts.py
structuredsnip-2025.12.21115854.dist-info/METADATA
structuredsnip-2025.12.21115854.dist-info/WHEEL
structuredsnip-2025.12.21115854.dist-info/top_level.txt
structuredsnip-2025.12.21115854.dist-info/RECORD
