Metadata-Version: 2.4
Name: structuredsnip
Version: 2025.12.21115854
Summary: A new package that takes unstructured text input from users and returns structured, categorized feedback or suggestions. It uses pattern matching to ensure responses follow a consistent format, such a
Author-email: structuredsnip <hi@eugene.plus>
License: MIT
Project-URL: Homepage, https://github.com/chigwell/structuredsnip
Requires-Python: >=3.9
Requires-Dist: langchain-llm7>=0.0.0
Requires-Dist: llmatch-messages>=0.0.0
Requires-Dist: langchain-core>=0.3.0
